django_periodiq/__init__.py
django_periodiq/apps.py
django_periodiq/setup.py
django_periodiq/management/__init__.py
django_periodiq/management/commands/__init__.py
django_periodiq/management/commands/runperiodiq.py
django_periodiq-0.3.0.dist-info/LICENSE
django_periodiq-0.3.0.dist-info/LICENSE_Bogdanp_django_dramatiq
django_periodiq-0.3.0.dist-info/METADATA
django_periodiq-0.3.0.dist-info/WHEEL
django_periodiq-0.3.0.dist-info/top_level.txt
django_periodiq-0.3.0.dist-info/RECORD
