Metadata-Version: 2.1
Name: django-periodiq
Version: 0.3.0
Summary: A Django app for Periodiq.
Home-page: https://github.com/q0w/django-periodiq/
Author: q0w
License: MIT
Classifier: Environment :: Web Environment
Classifier: Framework :: Django
Classifier: Framework :: Django :: 2.2
Classifier: Framework :: Django :: 3.2
Classifier: License :: OSI Approved :: MIT License
Classifier: Operating System :: OS Independent
Classifier: Programming Language :: Python :: 3
Classifier: Programming Language :: Python :: 3 :: Only
Classifier: Programming Language :: Python :: 3.7
Classifier: Programming Language :: Python :: 3.8
Classifier: Programming Language :: Python :: 3.9
Classifier: Programming Language :: Python :: 3.10
Classifier: Programming Language :: Python :: Implementation :: CPython
Requires-Python: >=3.7
License-File: licenses/LICENSE_Bogdanp_django_dramatiq
License-File: LICENSE
Requires-Dist: django-dramatiq (>=0.11.0)
Requires-Dist: periodiq
